{
  "metadata": [
    {
      "src": [{ "files": ["src/artifacts/bin/BD.Common8.Bcl/**/BD.Common8.Bcl.dll"]}],
      "dest": "api/BD.Common8.Bcl"
    },
    {
      "src": [{ "files": ["src/artifacts/bin/BD.Common8.Bcl.Compat/**/BD.Common8.Bcl.Compat.dll"]}],
      "dest": "api/BD.Common8.Bcl.Compat"
    },
    {
      "src": [{ "files": ["src/artifacts/bin/BD.Common8.Ipc/**/BD.Common8.Ipc.dll"]}],
      "dest": "api/BD.Common8.Ipc"
    },
    {
      "src": [{ "files": ["src/artifacts/bin/BD.Common8.Ipc.Client/**/BD.Common8.Ipc.Client.dll"]}],
      "dest": "api/BD.Common8.Ipc.Client"
    },
    {
      "src": [{ "files": ["src/artifacts/bin/BD.Common8.Ipc.Server/**/BD.Common8.Ipc.Server.dll"]}],
      "dest": "api/BD.Common8.Ipc.Server"
    },
    {
      "src": [{ "files": ["src/artifacts/bin/BD.Common8.Orm.EFCore/**/BD.Common8.Orm.EFCore.dll"]}],
      "dest": "api/BD.Common8.Orm.EFCore"
    },
    {
      "src": [{ "files": ["src/artifacts/bin/BD.Common8.Primitives.ApiResponse/**/BD.Common8.Primitives.ApiResponse.dll"]}],
      "dest": "api/BD.Common8.Primitives.ApiResponse"
    },
    {
      "src": [{ "files": ["src/artifacts/bin/BD.Common8.Primitives.ApiRsp/**/BD.Common8.Primitives.ApiRsp.dll"]}],
      "dest": "api/BD.Common8.Primitives.ApiRsp"
    },
    {
      "src": [{ "files": ["src/artifacts/bin/BD.Common8.Primitives.PersonalData.BirthDate/**/BD.Common8.Primitives.PersonalData.BirthDate.dll"]}],
      "dest": "api/BD.Common8.Primitives.PersonalData.BirthDate"
    },
    {
      "src": [{ "files": ["src/artifacts/bin/BD.Common8.Primitives.PersonalData.PhoneNumber/**/BD.Common8.Primitives.PersonalData.PhoneNumber.dll"]}],
      "dest": "api/BD.Common8.Primitives.PersonalData.PhoneNumber"
    },
    {
      "src": [{ "files": ["src/artifacts/bin/BD.Common8.Primitives/**/BD.Common8.Primitives.dll"]}],
      "dest": "api/BD.Common8.Primitives"
    },
    {
      "src": [{ "files": ["src/artifacts/bin/BD.Common8.Primitives.District/**/BD.Common8.Primitives.District.dll"]}],
      "dest": "api/BD.Common8.Primitives.District"
    },
    {
      "src": [{ "files": ["src/artifacts/bin/BD.Common8.Security/**/BD.Common8.Security.dll"]}],
      "dest": "api/BD.Common8.Security"
    },
    {
      "src": [{ "files": ["src/artifacts/bin/BD.Common8.UserInput.ModelValidator/**/BD.Common8.UserInput.ModelValidator.dll"]}],
      "dest": "api/BD.Common8.UserInput.ModelValidator"
    },
    {
      "src": [{ "files": ["src/artifacts/bin/BD.Common8.SourceGenerator.Shared/**/BD.Common8.SourceGenerator.Shared.dll"]}],
      "dest": "api/BD.Common8.SourceGenerator.Shared"
    },
    {
      "src": [{ "files": ["src/artifacts/bin/BD.Common8.Pinyin/**/BD.Common8.Pinyin.dll"]}],
      "dest": "api/BD.Common8.Pinyin"
    },
    {
      "src": [{ "files": ["src/artifacts/bin/BD.Common8.Pinyin.ChnCharInfo/**/BD.Common8.Pinyin.ChnCharInfo.dll"]}],
      "dest": "api/BD.Common8.Pinyin.ChnCharInfo"
    },
    {
      "src": [{ "files": ["src/artifacts/bin/BD.Common8.Pinyin.CoreFoundation/**/BD.Common8.Pinyin.CoreFoundation.dll"]}],
      "dest": "api/BD.Common8.Pinyin.CoreFoundation"
    },
    {
      "src": [{ "files": ["src/artifacts/bin/BD.Common8.AspNetCore/**/BD.Common8.AspNetCore.dll"]}],
      "dest": "api/BD.Common8.AspNetCore"
    },
    {
      "src": [{ "files": ["src/artifacts/bin/BD.Common8.AspNetCore.Identity/**/BD.Common8.AspNetCore.Identity.dll"]}],
      "dest": "api/BD.Common8.AspNetCore.Identity"
    },
    {
      "src": [{ "files": ["src/artifacts/bin/BD.Common8.AspNetCore.Identity.BackManage/**/BD.Common8.AspNetCore.Identity.BackManage.dll"]}],
      "dest": "api/BD.Common8.AspNetCore.Identity.BackManage"
    },
    {
      "src": [{ "files": ["src/artifacts/bin/BD.Common8.Essentials/**/BD.Common8.Essentials.dll"]}],
      "dest": "api/BD.Common8.Essentials"
    },
    {
      "src": [{ "files": ["src/artifacts/bin/BD.Common8.Essentials.Implementation/**/BD.Common8.Essentials.Implementation.dll"]}],
      "dest": "api/BD.Common8.Essentials.Implementation"
    },
    {
      "src": [{ "files": ["src/artifacts/bin/BD.Common8.Essentials.Implementation.Avalonia/**/BD.Common8.Essentials.Implementation.Avalonia.dll"]}],
      "dest": "api/BD.Common8.Essentials.Implementation.Avalonia"
    },
    {
      "src": [{ "files": ["src/artifacts/bin/BD.Common8.Http.ClientFactory/**/BD.Common8.Http.ClientFactory.dll"]}],
      "dest": "api/BD.Common8.Http.ClientFactory"
    },
    {
      "src": [{ "files": ["src/artifacts/bin/BD.Common8.Http.ClientFactory.Server/**/BD.Common8.Http.ClientFactory.Server.dll"]}],
      "dest": "api/BD.Common8.Http.ClientFactory.Server"
    },
    {
      "src": [{ "files": ["src/artifacts/bin/BD.Common8.Repositories/**/BD.Common8.Repositories.dll"]}],
      "dest": "api/BD.Common8.Repositories"
    },
    {
      "src": [{ "files": ["src/artifacts/bin/BD.Common8.Repositories.EFCore/**/BD.Common8.Repositories.EFCore.dll"]}],
      "dest": "api/BD.Common8.Repositories.EFCore"
    },
    {
      "src": [{ "files": ["src/artifacts/bin/BD.Common8.Repositories.SQLitePCL/**/BD.Common8.Repositories.SQLitePCL.dll"]}],
      "dest": "api/BD.Common8.Repositories.SQLitePCL"
    },
    {
      "src": [{ "files": ["src/artifacts/bin/BD.Common8.Settings5/**/BD.Common8.Settings5.dll"]}],
      "dest": "api/BD.Common8.Settings5"
    },
    {
      "src": [{ "files": ["src/artifacts/bin/BD.Common8.Settings5.Backend/**/BD.Common8.Settings5.Backend.dll"]}],
      "dest": "api/BD.Common8.Settings5.Backend"
    },
    {
      "src": [{ "files": ["src/artifacts/bin/BD.Common8.Settings5.Frontend/**/BD.Common8.Settings5.Frontend.dll"]}],
      "dest": "api/BD.Common8.Settings5.Frontend"
    },
    {
      "src": [{ "files": ["src/artifacts/bin/BD.Common8.Crawler/**/BD.Common8.Crawler.dll"]}],
      "dest": "api/BD.Common8.Crawler"
    },
    {
      "src": [{ "files": ["src/artifacts/bin/BD.Common8.SmsSender/**/BD.Common8.SmsSender.dll"]}],
      "dest": "api/BD.Common8.SmsSender"
    },
    {
      "src": [{ "files": ["src/artifacts/bin/BD.Common8.Toast/**/BD.Common8.Toast.dll"]}],
      "dest": "api/BD.Common8.Toast"
    }
  ],
  "build": {
    "content": [
      {
        "files": [
          "articles/**.md",
          "articles/**.html",
          "*.html",
          "articles/**/toc.yml",
          "toc.yml",
          "*.md"
        ]
      },
      {
        "files": [
          "api/**.yml",
          "api/index.md",
          "api/**/**.yml"
        ]
      }  
    ],
    "resource": [
      {
        "files": [
          "images/**",
          "res/DocFXIcon.png",
          "articles/aes.html",
          "articles/rsa.html",
          "README.md"
        ]
      }
    ],
    "output": "_site",
    "globalMetadata": {   
      "_appTitle": "BD.Common8 文档",
      "_appName": "Common8",
      "_appLogoPath": "res/DocFXIcon.png",
      "_appFooter": "©️ 江苏蒸汽凡星科技有限公司. All rights reserved.",
      "_disableBreadcrumb": true
    },
    "globalMetadataFiles": [],
    "fileMetadataFiles": [],
    "template": [
      "default",
      "modern",
      "templates/default"
    ],
    "keepFileLink": false,
    "disableGitFeatures": false
  }
}