
{"order":100,"items":[{"name":"BD.Common8.Extensions","href":"BD.Common8.Extensions.html","topicHref":"BD.Common8.Extensions.html","topicUid":"BD.Common8.Extensions","type":"Namespace","items":[{"name":"ApiResponseExtensions","href":"BD.Common8.Extensions.ApiResponseExtensions.html","topicHref":"BD.Common8.Extensions.ApiResponseExtensions.html","topicUid":"BD.Common8.Extensions.ApiResponseExtensions","type":"Class"}]},{"name":"BD.Common8.Models","href":"BD.Common8.Models.html","topicHref":"BD.Common8.Models.html","topicUid":"BD.Common8.Models","type":"Namespace","items":[{"name":"ApiResponse","href":"BD.Common8.Models.ApiResponse.html","topicHref":"BD.Common8.Models.ApiResponse.html","topicUid":"BD.Common8.Models.ApiResponse","type":"Class"},{"name":"ApiResponse<T>","href":"BD.Common8.Models.ApiResponse-1.html","topicHref":"BD.Common8.Models.ApiResponse-1.html","topicUid":"BD.Common8.Models.ApiResponse`1","type":"Class"}]},{"name":"BD.Common8.Models.Abstractions","href":"BD.Common8.Models.Abstractions.html","topicHref":"BD.Common8.Models.Abstractions.html","topicUid":"BD.Common8.Models.Abstractions","type":"Namespace","items":[{"name":"IApiResponse","href":"BD.Common8.Models.Abstractions.IApiResponse.html","topicHref":"BD.Common8.Models.Abstractions.IApiResponse.html","topicUid":"BD.Common8.Models.Abstractions.IApiResponse","type":"Interface"},{"name":"IApiResponse<T>","href":"BD.Common8.Models.Abstractions.IApiResponse-1.html","topicHref":"BD.Common8.Models.Abstractions.IApiResponse-1.html","topicUid":"BD.Common8.Models.Abstractions.IApiResponse`1","type":"Interface"}]}],"memberLayout":"SamePage","name":null}
