
{"order":100,"items":[{"name":"Microsoft.Extensions.DependencyInjection","href":"Microsoft.Extensions.DependencyInjection.html","topicHref":"../BD.Common8.AspNetCore/Microsoft.Extensions.DependencyInjection.html","topicUid":"Microsoft.Extensions.DependencyInjection","type":"Namespace","items":[{"name":"ServiceCollectionExtensions","href":"Microsoft.Extensions.DependencyInjection.ServiceCollectionExtensions.html","topicHref":"../BD.Common8.AspNetCore/Microsoft.Extensions.DependencyInjection.ServiceCollectionExtensions.html","topicUid":"Microsoft.Extensions.DependencyInjection.ServiceCollectionExtensions","type":"Class"}]}],"memberLayout":"SamePage","name":null}
